cloe_extensions/__init__.py
cloe_extensions/converter/__init__.py
cloe_extensions/converter/converter.py
cloe_extensions/converter/main.py
cloe_extensions/converter/cli/__init__.py
cloe_extensions/converter/cli/convert_csv_to_db_model.py
cloe_extensions/crawler/__init__.py
cloe_extensions/crawler/main.py
cloe_extensions/crawler/cli/__init__.py
cloe_extensions/crawler/cli/crawl_mssql.py
cloe_extensions/crawler/cli/crawl_sap.py
cloe_extensions/crawler/cli/crawl_snowflake.py
cloe_extensions/crawler/crawlers/__init__.py
cloe_extensions/crawler/crawlers/mssql_crawler.py
cloe_extensions/crawler/crawlers/sap_crawler.py
cloe_extensions/crawler/crawlers/snowflake_crawler.py
cloe_extensions/crawler/templates/__init__.py
cloe_extensions/crawler/templates/mssql/__init__.py
cloe_extensions/crawler/templates/mssql/column_retrieve.sql.j2
cloe_extensions/crawler/templates/mssql/schema_retrieve.sql.j2
cloe_extensions/crawler/templates/mssql/table_retrieve.sql.j2
cloe_extensions/crawler/templates/snowflake/__init__.py
cloe_extensions/crawler/templates/snowflake/column_retrieve.sql.j2
cloe_extensions/crawler/templates/snowflake/schema_retrieve.sql.j2
cloe_extensions/crawler/templates/snowflake/table_retrieve.sql.j2
cloe_extensions/crawler/utils/__init__.py
cloe_extensions/crawler/utils/repository.py
cloe_extensions/database_transformation/__init__.py
cloe_extensions/database_transformation/main.py
cloe_extensions/database_transformation/transformer.py
cloe_extensions/database_transformation/cli/__init__.py
cloe_extensions/database_transformation/cli/transform_db_model_to_snowflake.py
cloe_extensions/extractor/__init__.py
cloe_extensions/extractor/db2fs_fs2db_generator.py
cloe_extensions/extractor/main.py
cloe_extensions/snowflake_access_control/__init__.py
cloe_extensions/snowflake_access_control/main.py
cloe_extensions/snowflake_access_control/cli/__init__.py
cloe_extensions/snowflake_access_control/cli/deploy_roles.py
CloeExtensions-20240129.2.dist-info/LICENSE
CloeExtensions-20240129.2.dist-info/METADATA
CloeExtensions-20240129.2.dist-info/WHEEL
CloeExtensions-20240129.2.dist-info/entry_points.txt
CloeExtensions-20240129.2.dist-info/top_level.txt
CloeExtensions-20240129.2.dist-info/RECORD
